cbcreator/__init__.py
cbcreator/__main__.py
cbcreator/cbcreator.py
cbcreator/resources/fonts/001.ttf
cbcreator/resources/fonts/002.ttf
cbcreator/resources/fonts/003.ttf
cbcreator/resources/fonts/004.ttf
cbcreator/resources/fonts/__init__.py
cbcreator-1.0.dist-info/LICENSE
cbcreator-1.0.dist-info/METADATA
cbcreator-1.0.dist-info/WHEEL
cbcreator-1.0.dist-info/entry_points.txt
cbcreator-1.0.dist-info/top_level.txt
cbcreator-1.0.dist-info/RECORD
