Metadata-Version: 2.1
Name: cbcreator
Version: 1.0
Summary: Automatic class band creator
Home-page: https://github.com/myzhang1029/cbcreator
Author: Zhang Maiyun
Author-email: myzhang1029@hotmail.com
License: UNKNOWN
Platform: UNKNOWN
Classifier: Development Status :: 2 - Pre-Alpha
Classifier: Environment :: Console
Classifier: Intended Audience :: Information Technology
Classifier: License :: OSI Approved :: Apache Software License
Classifier: Operating System :: OS Independent
Classifier: Programming Language :: Python :: 3
Requires-Python: >=3.5
Requires-Dist: pillow
